skidge/__init__.py
skidge/__main__.py
skidge-0.2.0.dist-info/METADATA
skidge-0.2.0.dist-info/WHEEL
skidge-0.2.0.dist-info/entry_points.txt
skidge-0.2.0.dist-info/top_level.txt
skidge-0.2.0.dist-info/RECORD
