Metadata-Version: 2.2
Name: skidge
Version: 0.2.0
Summary: A Skype/XMPP gateway
Author-email: Nicolas Cedilnik <nicoco@nicoco.fr>
License:                     GNU AFFERO GENERAL PUBLIC LICENSE
Project-URL: Homepage, https://codeberg.org/slidge/skidge
Project-URL: Issues, https://codeberg.org/slidge/skidge/issues
Project-URL: Repository, https://codeberg.org/slidge/skidge
Project-URL: Chat room, https://conference.nicoco.fr:5281/muc_log/slidge/
Project-URL: Documentation, https://slidge.codeberg.page/docs/skidge/main
Keywords: xmpp,gateway,bridge,instant messaging,skype
Classifier: Topic :: Internet :: XMPP
Requires-Python: >=3.11
Requires-Dist: skpy>=0.11
Requires-Dist: slidge>=0.2.3.post1
